cli/__init__.py
cli/cli.py
eit_dash/__init__.py
eit_dash/app.py
eit_dash/callbacks/__init__.py
eit_dash/callbacks/analyze_callbacks.py
eit_dash/callbacks/load_callbacks.py
eit_dash/callbacks/preprocessing_callbacks.py
eit_dash/definitions/__init__.py
eit_dash/definitions/constants.py
eit_dash/definitions/element_ids.py
eit_dash/definitions/layout_styles.py
eit_dash/definitions/option_lists.py
eit_dash/main.py
eit_dash/pages/__init__.py
eit_dash/pages/analyze.py
eit_dash/pages/dummy.py
eit_dash/pages/load.py
eit_dash/pages/preprocessing.py
eit_dash/utils/__init__.py
eit_dash/utils/common.py
eit_dash/utils/data_singleton.py
eit_dash-0.0.1.dist-info/LICENSE
eit_dash-0.0.1.dist-info/METADATA
eit_dash-0.0.1.dist-info/WHEEL
eit_dash-0.0.1.dist-info/entry_points.txt
eit_dash-0.0.1.dist-info/RECORD
