Metadata-Version: 2.1
Name: eit_dash
Version: 0.0.1
Summary: GUI to load and analyze image data from electrical impedance tomography (EIT)
License: Apache 2.0
Keywords: EIT - Electrical Impedance Tomography,GUI
Author: Your Name
Author-email: you@example.com
Requires-Python: >=3.10,<3.13
Classifier: Development Status :: 2 - Pre-Alpha
Classifier: Intended Audience :: Developers
Classifier: License :: OSI Approved :: Apache Software License
Classifier: License :: Other/Proprietary License
Classifier: Natural Language :: English
Classifier: Programming Language :: Python :: 3
Classifier: Programming Language :: Python :: 3.10
Classifier: Programming Language :: Python :: 3.11
Classifier: Programming Language :: Python :: 3.12
Requires-Dist: click (>=8.1.7,<9.0.0)
Requires-Dist: dash-bootstrap-components (>=1.4.1,<2.0.0)
Requires-Dist: dash[testing] (>=2.11.1,<3.0.0)
Requires-Dist: eitprocessing (>=1.0.2,<2.0.0)
Requires-Dist: numpy (>=1.25.2,<2.0.0)
Requires-Dist: pandas (>=2.0.3,<3.0.0)
Requires-Dist: ruff (>=0.4.9,<0.5.0)
Project-URL: Bug Tracker, https://github.com/EIT-ALIVE/eit_dash/issues
Project-URL: repository, https://github.com/EIT-ALIVE/eit_dash
